BalanceSpider/BtcBalanceSpider.py
BalanceSpider/XrpBalanceSpider.py
BalanceSpider/__init__.py
BalanceSpider-0.0.9.dist-info/METADATA
BalanceSpider-0.0.9.dist-info/WHEEL
BalanceSpider-0.0.9.dist-info/top_level.txt
BalanceSpider-0.0.9.dist-info/RECORD
