Metadata-Version: 2.1
Name: BalanceSpider
Version: 0.0.9
Summary: simple tool
Home-page: https://github.com/Nevquit/monitor_msg_tools
Author: vSir
Author-email: weiguo341@gmail.com
Classifier: Programming Language :: Python :: 3
Classifier: License :: OSI Approved :: MIT License
Classifier: Operating System :: OS Independent
Requires-Dist: lxml (==4.5.0)
Requires-Dist: requests
